csr_azure_utils-2.0.6.data/scripts/clear_aad_application_list.py
csr_azure_utils-2.0.6.data/scripts/clear_default_aad_app.py
csr_azure_utils-2.0.6.data/scripts/clear_token.py
csr_azure_utils-2.0.6.data/scripts/refresh_token.py
csr_azure_utils-2.0.6.data/scripts/set_default_aad_app.py
csr_azure_utils-2.0.6.data/scripts/show_auth_applications.py
csr_cloud/__init__.py
csr_cloud/aad_auth.py
csr_cloud/as_azure.py
csr_cloud/auth_mgr.py
csr_cloud/azure_utils.py
csr_cloud/blob_utils.py
csr_cloud/clear_aad_application_list.py
csr_cloud/clear_default_aad_app.py
csr_cloud/clear_token.py
csr_cloud/csr_cloud.py
csr_cloud/eventhub_utils.py
csr_cloud/file_utils.py
csr_cloud/general_utils.py
csr_cloud/ha_azure.py
csr_cloud/meta_utils.py
csr_cloud/metric_utils.py
csr_cloud/msi_auth.py
csr_cloud/refresh_token.py
csr_cloud/servicebus_utils.py
csr_cloud/set_default_aad_app.py
csr_cloud/show_auth_applications.py
csr_cloud/token_api.py
csr_cloud/token_svr.py
csr_azure_utils-2.0.6.dist-info/LICENSE
csr_azure_utils-2.0.6.dist-info/METADATA
csr_azure_utils-2.0.6.dist-info/WHEEL
csr_azure_utils-2.0.6.dist-info/top_level.txt
csr_azure_utils-2.0.6.dist-info/RECORD
