Metadata-Version: 2.1
Name: csr-azure-utils
Version: 2.0.6
Summary: Utilities for csr1000v on Azure
Home-page: https://github4-chn.cisco.com/csr1000v-azure/csr_azure_utils
Author: Cisco Systems Inc.
Author-email: csr-cloud-dev@cisco.com
License: MIT
Download-URL: https://github4-chn.cisco.com/csr1000v-azure/csr_azure_utils/archive/2.0.6.tar.gz
Keywords: cisco,azure,guestshell,csr1000v
Platform: UNKNOWN
Classifier: Development Status :: 3 - Alpha
Classifier: Intended Audience :: Developers
Classifier: License :: OSI Approved :: MIT License
Classifier: Programming Language :: Python :: 2.7
Classifier: Programming Language :: Python :: 3.6
Requires-Dist: cryptography (==2.9.2)
Requires-Dist: python-crontab (==2.5.1)
Requires-Dist: pathlib (==1.0.1)
Requires-Dist: configparser (==4.0.2)
Requires-Dist: pyopenssl (==19.1.0)
Requires-Dist: msrest (==0.6.16)
Requires-Dist: msrestazure (==0.6.3)
Requires-Dist: paramiko (==2.7.1)
Requires-Dist: future (==0.18.2)
Requires-Dist: azure-storage-file (==2.1.0)
Requires-Dist: azure-storage-blob (==12.3.2)
Requires-Dist: azure-storage-common (==2.1.0)
Requires-Dist: azure-storage-nspkg (==3.1.0)
Requires-Dist: requests (==2.23.0)
